<?xml version = '1.0' encoding = 'UTF-8'?>
<FKIndexAssociation class="oracle.dbtools.crest.model.design.relational.FKIndexAssociation" directorySegmentName="seg_0" id="B73A833D-5935-C56F-8C06-BF316FAFEDB0" containerWithKeyObject="61838862-E36C-DEBF-D99D-B57AA95C3A7C" localFKIndex="C7A874A6-9CE7-E9B4-D898-A71C704AF809" name="Vozacka_dozvola_Vozac_FK">
<createdBy>lukaj</createdBy>
<createdTime>2023-11-13 17:48:05 UTC</createdTime>
<ownerDesignName>Ui projekat</ownerDesignName>
<referredTableLongName>Vozac</referredTableLongName>
<deleteRule>NO ACTION</deleteRule>
<referredTableID>3EA7A567-842D-118E-C626-D6C491561566</referredTableID>
<keyObject>7388AD50-D50C-DEE0-1134-84BA429D48FB</keyObject>
<referredKeyID>7388AD50-D50C-DEE0-1134-84BA429D48FB</referredKeyID>
<mandatory>true</mandatory>
<refColNames>vozac_id</refColNames>
<transferable>true</transferable>
<rely>false</rely>
<columnDependencyConstraintGenerateInDDL>true</columnDependencyConstraintGenerateInDDL>
</FKIndexAssociation>
